{
  "editors": [
    "Daniel Kunin",
    "Eric J. Michaud",
    "Florentin Guth",
    "Jamie Simon"
  ],
  "team": [
    "Alex Atanasov",
    "Enric Boix-Adser\u00e0",
    "Blake Bordelon",
    "Jeremy Cohen",
    "Nikhil Ghosh",
    "Florentin Guth",
    "Arthur Jacot",
    "Mason Kamb",
    "Dhruva Karkada",
    "Daniel Kunin",
    "Eric J. Michaud",
    "Berkan Ottlik",
    "Jamie Simon",
    "Joey Turnbull"
  ],
  "contributors": [
    {
      "name": "Alex Atanasov",
      "url": "https://abatanasov.com/",
      "affiliation": "Harvard",
      "photo": "static/people/alex-atanasov.png"
    },
    {
      "name": "Jeremy Bernstein",
      "url": "https://jeremybernste.in/"
    },
    {
      "name": "Blake Bordelon",
      "url": "https://blakebordelon.github.io/",
      "affiliation": "Harvard",
      "photo": "static/people/blake-bordelon.png"
    },
    {
      "name": "Jeremy Cohen",
      "url": "https://jmcohen.github.io/",
      "affiliation": "Flatiron Institute",
      "photo": "static/people/jeremy-cohen.png"
    },
    {
      "name": "Alex Damian",
      "url": "https://web.math.princeton.edu/~ad27/"
    },
    {
      "name": "Nikhil Ghosh",
      "url": "https://nikhil-ghosh-berkeley.github.io/",
      "affiliation": "Flatiron Institute",
      "photo": "static/people/nikhil-ghosh.png"
    },
    {
      "name": "Enric Boix-Adser\u00e0",
      "url": "https://eboix.github.io/",
      "affiliation": "University of Pennsylvania",
      "photo": "static/people/enric-boix-adsera.png"
    },
    {
      "name": "Florentin Guth",
      "url": "https://florentinguth.github.io/",
      "affiliation": "NYU and the Flatiron Institute",
      "photo": "static/people/florentin-guth.png"
    },
    {
      "name": "Arthur Jacot",
      "url": "https://sites.google.com/view/arthurjacot",
      "affiliation": "New York University",
      "photo": "static/people/arthur-jacot.png"
    },
    {
      "name": "Dhruva Karkada",
      "url": "https://dkarkada.xyz/",
      "affiliation": "UC Berkeley",
      "photo": "static/people/dhruva-karkada.png"
    },
    {
      "name": "Daniel Kunin",
      "url": "https://daniel-kunin.com/",
      "affiliation": "UC Berkeley",
      "photo": "static/people/daniel-kunin.png"
    },
    {
      "name": "Alex Meterez",
      "url": "https://alexandrumeterez.github.io/"
    },
    {
      "name": "Mason Kamb",
      "url": "https://scholar.google.com/citations?user=H-yl_JMAAAAJ&hl=en",
      "affiliation": "Stanford",
      "photo": "static/people/mason-kamb.png"
    },
    {
      "name": "Eric J. Michaud",
      "url": "https://ericjmichaud.com/",
      "affiliation": "Astera Institute / Simplex AI Safety",
      "photo": "static/people/eric-michaud.png"
    },
    {
      "name": "Theodor Misiakiewicz",
      "url": "https://misiakie.github.io/"
    },
    {
      "name": "Berkan Ottlik",
      "url": "https://berkan.xyz/",
      "affiliation": "University of Pennsylvania",
      "photo": "static/people/berkan-ottlik.png"
    },
    {
      "name": "Adit Radha",
      "url": "https://aditradha.com/"
    },
    {
      "name": "Jamie Simon",
      "url": "https://jamiesimon.io/",
      "affiliation": "UC Berkeley and Imbue",
      "photo": "static/people/jamie-simon.png"
    },
    {
      "name": "Mark Rhee",
      "url": "https://mrkdh16.github.io",
      "affiliation": "UC Berkeley"
    },
    {
      "name": "Joey Turnbull",
      "url": "https://joeyturn.github.io/",
      "affiliation": "UC Berkeley",
      "photo": "static/people/joey-turnbull.png"
    },
    {
      "name": "Jacob Zavatone-Veth",
      "url": "https://jzv.io/"
    }
  ]
}